{
  "name": "shades-of-purple",
  "type": "dark",
  "background": "#1e1d40",
  "foreground": "#ffffff",
  "black": "#000000",
  "red": "#d90429",
  "green": "#3ad900",
  "yellow": "#ffe700",
  "blue": "#6943ff",
  "magenta": "#ff2c70",
  "cyan": "#00c5c7",
  "white": "#c7c7c7",
  "brblack": "#686868",
  "brred": "#f92a1c",
  "brgreen": "#43d426",
  "bryellow": "#f1d000",
  "brblue": "#6871ff",
  "brmagenta": "#ff77ff",
  "brcyan": "#79e8fb",
  "brwhite": "#ffffff",
  "cursor_text": "#fefff4",
  "cursor_color": "#fad000",
  "selection_background": "#b362ff",
  "selection_text": "#c2c2c2"
}
