{
  "name": "Abernathy",
  "type": "dark",
  "background": "#111416",
  "foreground": "#eeeeec",
  "black": "#000000",
  "red": "#cd0000",
  "green": "#00cd00",
  "yellow": "#cdcd00",
  "blue": "#1093f5",
  "magenta": "#cd00cd",
  "cyan": "#00cdcd",
  "white": "#faebd7",
  "brblack": "#404040",
  "brred": "#ff0000",
  "brgreen": "#00ff00",
  "bryellow": "#ffff00",
  "brblue": "#11b5f6",
  "brmagenta": "#ff00ff",
  "brcyan": "#00ffff",
  "brwhite": "#ffffff",
  "cursor_text": "#ffffff",
  "cursor_color": "#bbbbbb",
  "selection_background": "#eeeeec",
  "selection_text": "#333333"
}
