{
  "name": "OneHalfLight",
  "type": "light",
  "url": "",
  "background": "#fafafa",
  "foreground": "#383a42",
  "black": "#383a42",
  "blue": "#0184bc",
  "cyan": "#0997b3",
  "green": "#50a14f",
  "magenta": "#a626a4",
  "red": "#e45649",
  "white": "#fafafa",
  "yellow": "#c18401",
  "brblack": "#4f525e",
  "brblue": "#61afef",
  "brcyan": "#56b6c2",
  "brgreen": "#98c379",
  "brmagenta": "#c678dd",
  "brred": "#e06c75",
  "brwhite": "#ffffff",
  "bryellow": "#e5c07b",
  "cursor_text": "#383a42",
  "cursor_color": "#bfceff",
  "selection_background": "#bfceff",
  "selection_text": "#383a42"
}
