{
  "name": "Red Sands",
  "type": "light",
  "url": "",
  "background": "#7a251e",
  "foreground": "#d7c9a7",
  "black": "#000000",
  "blue": "#0072ff",
  "cyan": "#00bbbb",
  "green": "#00bb00",
  "magenta": "#bb00bb",
  "red": "#ff3f00",
  "white": "#bbbbbb",
  "yellow": "#e7b000",
  "brblack": "#555555",
  "brblue": "#0072ae",
  "brcyan": "#55ffff",
  "brgreen": "#00bb00",
  "brmagenta": "#ff55ff",
  "brred": "#bb0000",
  "brwhite": "#ffffff",
  "bryellow": "#e7b000",
  "cursor_text": "#000000",
  "cursor_color": "#ffffff",
  "selection_background": "#a4a390",
  "selection_text": "#000000"
}
